Metadata-Version: 2.3
Name: pubmed-paper-fetcher-prajwal
Version: 0.1.1
Summary: A CLI tool to fetch PubMed papers and filter non-academic authors.
Author: Prajwal Parve
Author-email: parve99prajwal@gmail.com
Requires-Python: >=3.13
Classifier: Programming Language :: Python :: 3
Classifier: Programming Language :: Python :: 3.13
Requires-Dist: pandas (>=2.2.3,<3.0.0)
Requires-Dist: requests (>=2.32.3,<3.0.0)
Requires-Dist: typer (>=0.15.2,<0.16.0)
